odoo/addons/mgmtsystem_nonconformity_product/README.rst
odoo/addons/mgmtsystem_nonconformity_product/__init__.py
odoo/addons/mgmtsystem_nonconformity_product/__manifest__.py
odoo/addons/mgmtsystem_nonconformity_product/i18n/it.po
odoo/addons/mgmtsystem_nonconformity_product/i18n/mgmtsystem_extended_product.pot
odoo/addons/mgmtsystem_nonconformity_product/i18n/mgmtsystem_nonconformity_product.pot
odoo/addons/mgmtsystem_nonconformity_product/models/__init__.py
odoo/addons/mgmtsystem_nonconformity_product/models/mgmtsystem_nonconformity_product.py
odoo/addons/mgmtsystem_nonconformity_product/readme/CONFIGURE.rst
odoo/addons/mgmtsystem_nonconformity_product/readme/CONTRIBUTORS.rst
odoo/addons/mgmtsystem_nonconformity_product/readme/DESCRIPTION.rst
odoo/addons/mgmtsystem_nonconformity_product/readme/HISTORY.rst
odoo/addons/mgmtsystem_nonconformity_product/readme/INSTALL.rst
odoo/addons/mgmtsystem_nonconformity_product/readme/ROADMAP.rst
odoo/addons/mgmtsystem_nonconformity_product/readme/USAGE.rst
odoo/addons/mgmtsystem_nonconformity_product/static/description/icon.png
odoo/addons/mgmtsystem_nonconformity_product/static/description/index.html
odoo/addons/mgmtsystem_nonconformity_product/views/mgmtsystem_nonconformity_views.xml
odoo11_addon_mgmtsystem_nonconformity_product-11.0.1.0.0.99.dev3.dist-info/METADATA
odoo11_addon_mgmtsystem_nonconformity_product-11.0.1.0.0.99.dev3.dist-info/WHEEL
odoo11_addon_mgmtsystem_nonconformity_product-11.0.1.0.0.99.dev3.dist-info/top_level.txt
odoo11_addon_mgmtsystem_nonconformity_product-11.0.1.0.0.99.dev3.dist-info/RECORD
